cubicweb_sioc/__init__.py
cubicweb_sioc/__pkginfo__.py
cubicweb_sioc/site_cubicweb.py
cubicweb_sioc/views.py
cubicweb_sioc/i18n/en.po
cubicweb_sioc/i18n/es.po
cubicweb_sioc/i18n/fr.po
cubicweb_sioc-1.1.0.dist-info/METADATA
cubicweb_sioc-1.1.0.dist-info/WHEEL
cubicweb_sioc-1.1.0.dist-info/entry_points.txt
cubicweb_sioc-1.1.0.dist-info/top_level.txt
cubicweb_sioc-1.1.0.dist-info/RECORD
